clouditia/__init__.py
clouditia/client.py
clouditia/exceptions.py
clouditia/jobs.py
clouditia/magic.py
clouditia/py.typed
clouditia/results.py
clouditia-1.5.1.dist-info/licenses/LICENSE
clouditia-1.5.1.dist-info/METADATA
clouditia-1.5.1.dist-info/WHEEL
clouditia-1.5.1.dist-info/top_level.txt
clouditia-1.5.1.dist-info/RECORD
