Metadata-Version: 2.4
Name: clouditia
Version: 1.5.1
Summary: Execute Python and Shell code on remote GPU sessions
Author-email: Aina KIKI-SAGBE <support@clouditia.com>
Maintainer-email: Aina KIKI-SAGBE <support@clouditia.com>
License: MIT
Project-URL: Homepage, https://clouditia.com
Project-URL: Documentation, https://clouditia.com/docsapisession
Keywords: gpu,cloud,remote-execution,machine-learning,deep-learning,pytorch,tensorflow,cuda,jupyter,api
Classifier: Development Status :: 5 - Production/Stable
Classifier: Intended Audience :: Developers
Classifier: Intended Audience :: Science/Research
Classifier: License :: OSI Approved :: MIT License
Classifier: Operating System :: OS Independent
Classifier: Programming Language :: Python :: 3
Classifier: Programming Language :: Python :: 3.7
Classifier: Programming Language :: Python :: 3.8
Classifier: Programming Language :: Python :: 3.9
Classifier: Programming Language :: Python :: 3.10
Classifier: Programming Language :: Python :: 3.11
Classifier: Programming Language :: Python :: 3.12
Classifier: Topic :: Scientific/Engineering :: Artificial Intelligence
Classifier: Topic :: Software Development :: Libraries :: Python Modules
Classifier: Framework :: Jupyter
Requires-Python: >=3.7
License-File: LICENSE
Requires-Dist: requests>=2.20.0
Provides-Extra: dev
Requires-Dist: pytest>=6.0; extra == "dev"
Requires-Dist: pytest-cov; extra == "dev"
Requires-Dist: black; extra == "dev"
Requires-Dist: isort; extra == "dev"
Requires-Dist: flake8; extra == "dev"
Requires-Dist: mypy; extra == "dev"
Requires-Dist: twine; extra == "dev"
Requires-Dist: build; extra == "dev"
Provides-Extra: jupyter
Requires-Dist: ipython>=7.0; extra == "jupyter"
Requires-Dist: jupyter; extra == "jupyter"
Provides-Extra: s3
Requires-Dist: boto3>=1.26.0; extra == "s3"
Dynamic: license-file
